{
    "intentions": {
        "gravity": 2,
        "soper": {
            "weight": 2,
            "adm-ka": {
                "weight": 2,
                "reported_by": {
                    "MIRA-010": {
                        "1776828085": [
                            "crate.629B6E37AA3E1170"
                        ]
                    },
                    "1-MIRA-1": {
                        "1776861857": [
                            "crate.BF52F014828D3F84"
                        ]
                    }
                }
            }
        }
    }
}